odoo/addons/ssi_hr_expense_account_reimbursement/README.rst
odoo/addons/ssi_hr_expense_account_reimbursement/__init__.py
odoo/addons/ssi_hr_expense_account_reimbursement/__manifest__.py
odoo/addons/ssi_hr_expense_account_reimbursement/i18n/ssi_hr_expense_account_reimbursement.pot
odoo/addons/ssi_hr_expense_account_reimbursement/models/__init__.py
odoo/addons/ssi_hr_expense_account_reimbursement/models/employee_expense_account.py
odoo/addons/ssi_hr_expense_account_reimbursement/models/hr_reimbursement.py
odoo/addons/ssi_hr_expense_account_reimbursement/models/hr_reimbursement_line.py
odoo/addons/ssi_hr_expense_account_reimbursement/static/description/icon.png
odoo/addons/ssi_hr_expense_account_reimbursement/static/description/icon_timesheet.png
odoo/addons/ssi_hr_expense_account_reimbursement/views/employee_expense_account_view.xml
odoo/addons/ssi_hr_expense_account_reimbursement/views/hr_reimbursement_views.xml
odoo14_addon_ssi_hr_expense_account_reimbursement-14.0.1.4.0.dist-info/METADATA
odoo14_addon_ssi_hr_expense_account_reimbursement-14.0.1.4.0.dist-info/WHEEL
odoo14_addon_ssi_hr_expense_account_reimbursement-14.0.1.4.0.dist-info/top_level.txt
odoo14_addon_ssi_hr_expense_account_reimbursement-14.0.1.4.0.dist-info/RECORD
